drf_nested/__init__.py
drf_nested/mixins/__init__.py
drf_nested/mixins/base_nestable_mixin.py
drf_nested/mixins/base_nested_mixin.py
drf_nested/mixins/create_nested_mixin.py
drf_nested/mixins/generic_relation_mixin.py
drf_nested/mixins/nestable_mixin.py
drf_nested/mixins/through_mixin.py
drf_nested/mixins/unique_field_mixin.py
drf_nested/mixins/unique_together_mixin.py
drf_nested/mixins/update_nested_mixin.py
drf_nested/utils/__init__.py
drf_nested/utils/nested_exceptions.py
drf_nested/utils/queryset_to_instance.py
drf_nested-1.3.3.dist-info/LICENSE
drf_nested-1.3.3.dist-info/METADATA
drf_nested-1.3.3.dist-info/WHEEL
drf_nested-1.3.3.dist-info/RECORD
