Metadata-Version: 2.3
Name: drf-nested
Version: 1.3.3
Summary: DRF Nested
License: MIT
Author: Artur Veres
Author-email: artur8118@gmail.com
Requires-Python: >=3.10,<3.14
Classifier: License :: OSI Approved :: MIT License
Classifier: Programming Language :: Python :: 3
Classifier: Programming Language :: Python :: 3.10
Classifier: Programming Language :: Python :: 3.11
Classifier: Programming Language :: Python :: 3.12
Classifier: Programming Language :: Python :: 3.13
Requires-Dist: django (>=3.0.0,<6.0.0)
Requires-Dist: djangorestframework (>=3.16.0)
